vinces_selenium_extension/__init__.py
vinces_selenium_extension/logger.py
vinces_selenium_extension/selenium_initializer.py
vinces_selenium_extension/selenium_utils.py
vinces_selenium_extension/tests/__init__.py
vinces_selenium_extension-0.1.1.dist-info/METADATA
vinces_selenium_extension-0.1.1.dist-info/WHEEL
vinces_selenium_extension-0.1.1.dist-info/RECORD
