Metadata-Version: 2.1
Name: vinces_selenium_extension
Version: 0.1.1
Summary: Speeds up automation when using selenium
License: MIT
Author: vince
Author-email: contact.polymons@gmail.com
Requires-Python: >=3.10,<4.0
Classifier: License :: OSI Approved :: MIT License
Classifier: Programming Language :: Python :: 3
Classifier: Programming Language :: Python :: 3.10
Classifier: Programming Language :: Python :: 3.11
Classifier: Programming Language :: Python :: 3.12
Requires-Dist: python-dotenv (>=1.0.1,<2.0.0)
Requires-Dist: selenium (>=4.12.0,<5.0.0)
